tests/__init__.py
tests/conftest.py
tests/test_commands.py
tests/test_config.py
tests/test_grades.py
tests/test_grades_helpers.py
ugc/__init__.py
ugc/__main__.py
ugc/cli.py
ugc/commands.py
ugc/config.py
ugc/grades-template.json
ugc/grades.py
ugc/short_module_names.json
ugc/utils/__init__.py
ugc/utils/commands_helpers.py
ugc/utils/grades_helpers.py
ugc/utils/mathtools.py
uol_grades_calculator-0.13.1.dist-info/LICENSE
uol_grades_calculator-0.13.1.dist-info/METADATA
uol_grades_calculator-0.13.1.dist-info/WHEEL
uol_grades_calculator-0.13.1.dist-info/entry_points.txt
uol_grades_calculator-0.13.1.dist-info/top_level.txt
uol_grades_calculator-0.13.1.dist-info/RECORD
