Metadata-Version: 2.1
Name: uol-grades-calculator
Version: 0.13.1
Summary: Grades calculator for the BSc Computer Science at the University of London
Home-page: https://github.com/sglavoie/uol-grades-calculator
Author: Sébastien Lavoie
Author-email: sebastien@lavoie.dev
License: MIT
Project-URL: Documentation, https://uol-grades-calculator.readthedocs.io
Project-URL: Source, https://github.com/sglavoie/uol-grades-calculator
Project-URL: Tracker, https://github.com/sglavoie/uol-grades-calculator/issues
Classifier: Environment :: Console
Classifier: Intended Audience :: Education
Classifier: Intended Audience :: Developers
Classifier: License :: OSI Approved :: MIT License
Classifier: Programming Language :: Python :: 3
Classifier: Programming Language :: Python :: 3.8
Classifier: Natural Language :: English
Classifier: Operating System :: POSIX :: Linux
Classifier: Topic :: Education
Classifier: Topic :: Education :: Testing
Classifier: Topic :: Documentation :: Sphinx
Requires-Python: >=3.8
License-File: LICENSE
Requires-Dist: adjustText
Requires-Dist: click
Requires-Dist: matplotlib
Requires-Dist: pandas
Requires-Dist: tabulate
Provides-Extra: all
Requires-Dist: pytest (>=6.2.2) ; extra == 'all'
Requires-Dist: pytest-cov ; extra == 'all'
Provides-Extra: test
Requires-Dist: pytest (>=6.2.2) ; extra == 'test'
Requires-Dist: pytest-cov ; extra == 'test'
